airflow_python_sdk/__init__.py
airflow_python_sdk/api_client.py
airflow_python_sdk/configuration.py
airflow_python_sdk/exceptions.py
airflow_python_sdk/model_utils.py
airflow_python_sdk/rest.py
airflow_python_sdk/api/__init__.py
airflow_python_sdk/api/config_api.py
airflow_python_sdk/api/connection_api.py
airflow_python_sdk/api/dag_api.py
airflow_python_sdk/api/dag_run_api.py
airflow_python_sdk/api/event_log_api.py
airflow_python_sdk/api/import_error_api.py
airflow_python_sdk/api/monitoring_api.py
airflow_python_sdk/api/pool_api.py
airflow_python_sdk/api/task_instance_api.py
airflow_python_sdk/api/variable_api.py
airflow_python_sdk/api/x_com_api.py
airflow_python_sdk/apis/__init__.py
airflow_python_sdk/model/__init__.py
airflow_python_sdk/model/class_reference.py
airflow_python_sdk/model/clear_task_instance.py
airflow_python_sdk/model/collection_info.py
airflow_python_sdk/model/color.py
airflow_python_sdk/model/config.py
airflow_python_sdk/model/config_option.py
airflow_python_sdk/model/config_section.py
airflow_python_sdk/model/connection.py
airflow_python_sdk/model/connection_all_of.py
airflow_python_sdk/model/connection_collection.py
airflow_python_sdk/model/connection_collection_all_of.py
airflow_python_sdk/model/connection_collection_item.py
airflow_python_sdk/model/cron_expression.py
airflow_python_sdk/model/dag.py
airflow_python_sdk/model/dag_collection.py
airflow_python_sdk/model/dag_collection_all_of.py
airflow_python_sdk/model/dag_detail.py
airflow_python_sdk/model/dag_detail_all_of.py
airflow_python_sdk/model/dag_run.py
airflow_python_sdk/model/dag_run_collection.py
airflow_python_sdk/model/dag_run_collection_all_of.py
airflow_python_sdk/model/dag_state.py
airflow_python_sdk/model/dag_structure.py
airflow_python_sdk/model/dag_structure_collection.py
airflow_python_sdk/model/error.py
airflow_python_sdk/model/event_log.py
airflow_python_sdk/model/event_log_collection.py
airflow_python_sdk/model/event_log_collection_all_of.py
airflow_python_sdk-1.0.1.dist-info/LICENSE
airflow_python_sdk-1.0.1.dist-info/METADATA
airflow_python_sdk-1.0.1.dist-info/WHEEL
airflow_python_sdk-1.0.1.dist-info/top_level.txt
airflow_python_sdk-1.0.1.dist-info/RECORD
