Metadata-Version: 2.1
Name: airflow-python-sdk
Version: 1.0.1
Summary: Airflow API (Stable)
Home-page: UNKNOWN
Author: Zach Liu
Author-email: zach.z.liu@gmail.com
License: MIT
Project-URL: Bug Tracker, https://github.com/zachliu/airflow-python-sdk/issues
Project-URL: Source Code, https://github.com/zachliu/airflow-python-sdk
Project-URL: Download, https://github.com/zachliu/airflow-python-sdk/releases
Project-URL: Documentation, https://github.com/zachliu/airflow-python-sdk/blob/master/README.md
Keywords: OpenAPI,OpenAPI-Generator,Airflow API (Stable)
Platform: UNKNOWN
Requires-Python: >=3.6
Requires-Dist: urllib3 (>=1.25.3)
Requires-Dist: python-dateutil
Requires-Dist: nulltype
